ocredis/__init__.py
ocredis/client.py
ocredis/observability.py
ocredis-0.0.4.dist-info/METADATA
ocredis-0.0.4.dist-info/RECORD
ocredis-0.0.4.dist-info/WHEEL
ocredis-0.0.4.dist-info/namespace_packages.txt
ocredis-0.0.4.dist-info/top_level.txt
tests/__init__.py
tests/test_invoke_each_method.py
tests/test_propagate_exceptions.py
